[
  {
    "src": "https://cdn.imgchest.com/files/yrgcnzqqx94.jpg",
    "alt": "sample_91304bbb889f2184edcf5eca36224b9b.jpg",
    "tags": [
      "Athazel",
      "Yen",
      "Worship",
      "Rimming"
    ]
  },
  {
    "src": "https://cdn.imgchest.com/files/yd5cerww5r4.jpg",
    "alt": "sample_3739c341f1196319a2f935e3156429e2.jpg",
    "tags": [
      "Athazel",
      "Werewolf",
      "Dick",
      "Blowjob"
    ]
  },
  {
    "src": "https://cdn.imgchest.com/files/7mmc9rbba37.jpg",
    "alt": "sample_ae890130891985f615ff9338e289a305.jpg",
    "tags": [
      "Athazel",
      "Werewolf",
      "Dick",
      "Blowjob"
    ]
  },
  {
    "src": "https://cdn.imgchest.com/files/7lxcpdvval7.jpg",
    "alt": "sample_69dbf0066beab560a136d7733a07c3ba.jpg",
    "tags": [
      "Athazel",
      "Werewolf",
      "Dick",
      "Anal"
    ]
  },
  {
    "src": "https://cdn.imgchest.com/files/7ogcbk22aqy.jpg",
    "alt": "sample_4b995dc10c5b80977cac6cf010101e3c.jpg",
    "tags": [
      "Athazel",
      "Werewolf",
      "Dick",
      "Rimming"
    ]
  },
  {
    "src": "https://cdn.imgchest.com/files/7w6c2vkk9ay.jpg",
    "alt": "sample_c442c03e85f5667b3adf4833c8043903.jpg",
    "tags": [
      "Athazel",
      "Werewolf",
      "Ass",
      "Dick"
    ]
  },
  {
    "src": "https://cdn.imgchest.com/files/4jdcvjaax94.jpg",
    "alt": "sample_983fa1e2e011ab76eced73fd832c54bb.jpg",
    "tags": [
      "Athazel",
      "Werewolf",
      "Dick",
      "Blowjob"
    ]
  },
  {
    "src": "https://cdn.imgchest.com/files/ye3c2deevz4.jpg",
    "alt": "sample_dea531ff5d02557ad0183fe2b0546c7a.jpg",
    "tags": [
      "Athazel",
      "Werewolf",
      "Ass",
      "Dick"
    ]
  },
  {
    "src": "https://cdn.imgchest.com/files/739cx6qqzj7.jpg",
    "alt": "sample_ba495d20338a19a502e9484a40e8071a.jpg",
    "tags": [
      "Athazel",
      "Werewolf",
      "Ass",
      "Dick"
    ]
  },
  {
    "src": "https://cdn.imgchest.com/files/y2pckommqz7.jpg",
    "alt": "sample_61ae984ca72077cf321c3f566c9dd059.jpg",
    "tags": [
      "Athazel",
      "Werewolf",
      "Dick"
    ]
  },
  {
    "src": "https://cdn.imgchest.com/files/yq9c3ejjk64.jpg",
    "alt": "sample_1471f3efd7ab2765b07d6c3fd76b9c93.jpg",
    "tags": [
      "Athazel",
      "Werewolf",
      "Dick",
      "Anal"
    ]
  },
  {
    "src": "https://cdn.imgchest.com/files/7kzcab66pg7.jpg",
    "alt": "sample_5fdf38e7ff5db5dcd20f28d843c649cf.jpg",
    "tags": [
      "Athazel",
      "Werewolf",
      "Dick",
      "Cum"
    ]
  }
]