[
  {
    "src": "https://cdn.imgchest.com/files/y8xcn2jk5w4.png",
    "alt": "MiaRoom000b7pt.png",
    "tags": [
      "Apone"
    ]
  },
  {
    "src": "https://cdn.imgchest.com/files/45xcvqr92n7.png",
    "alt": "MiaRoom000b19pt.png",
    "tags": [
      "Apone"
    ]
  },
  {
    "src": "https://cdn.imgchest.com/files/4apc5we3pg4.png",
    "alt": "MiaRoom001b11pt.png",
    "tags": [
      "Apone"
    ]
  },
  {
    "src": "https://cdn.imgchest.com/files/46acq32bpw7.png",
    "alt": "MiaRoom002b6pt.png",
    "tags": [
      "Apone"
    ]
  },
  {
    "src": "https://cdn.imgchest.com/files/yvdcwg5dkoy.png",
    "alt": "MiaRoom003b10pt.png",
    "tags": [
      "Apone"
    ]
  }
]